.darglint
.dockerignore
.gitignore
.nvmrc
.pre-commit-config.yaml
.pylintrc
CHANGELOG.md
CONTRIBUTING.md
LICENSE
MANIFEST.in
Makefile
NOTICE
README-GB.md
README.md
RELEASE.md
build.sh
collect_env.py
extra-requirements.txt
im-policy.xml
info.py
package-lock.json
package.json
pyproject.toml
pyproject.toml-HOLD
pytest.ini
requirements.txt
setup.py
.github/CODE_OF_CONDUCT.md
.github/CODE_REVIEW_GUIDELINES.md
.github/changlog-header
.github/pull_request_template.md
.github/release-template.ejs
.github/slack-pypi.json
.github/ISSUE_TEMPLATE/---can-marie-do-this-.md
.github/ISSUE_TEMPLATE/---found-a-bug-and-i-solved-it.md
.github/ISSUE_TEMPLATE/---new-feature---discussion-needed.md
.github/ISSUE_TEMPLATE/---question---may-be-a-bug-.md
.github/ISSUE_TEMPLATE/config.yml
.github/workflows/codeql-analysis.yml
.github/workflows/commit-lint.yml
.github/workflows/force-docker-build.yml
.github/workflows/force-docs-build.yml
.github/workflows/force-release.yml
.run/batch_document_ocr.run.xml
.run/document_classifier.run.xml
.run/marie gateway.run.xml
.run/marie server - classifier.run.xml
.run/marie server - extract.run.xml
.run/marie server-deployment.run.xml
.run/template-matching app .run.xml
.vscode/launch.json
.vscode/settings.json
Dockerfiles/.dockerignore
Dockerfiles/cpu-310.Dockerfile
Dockerfiles/docker-compose.cli.yml
Dockerfiles/docker-compose.s3-debug.yml
Dockerfiles/docker-compose.s3.yml
Dockerfiles/docker-compose.storage.yml
Dockerfiles/docker-compose.yml
Dockerfiles/gpu-310.Dockerfile
Dockerfiles/gpu.Dockerfile
Dockerfiles/protogen-3.21.Dockerfile
Dockerfiles/protogen.Dockerfile
ansible/.env.example
ansible/README.md
ansible/env.sh
ansible/play-clean.sh
ansible/play-deploy-to-node.sh
ansible/play-gpu-info.sh
ansible/play-gpu-undervolt.sh
ansible/play-info.sh
ansible/play-log-driver-rotate.sh
ansible/play-pull-image.sh
ansible/play-restart-daemon.sh
ansible/play-start-node.sh
ansible/play-status-node.sh
ansible/play-stop-node.sh
ansible/play-validate.sh
marie_ai.egg-info/PKG-INFO
marie_ai.egg-info/SOURCES.txt
marie_ai.egg-info/dependency_links.txt
marie_ai.egg-info/entry_points.txt
marie_ai.egg-info/not-zip-safe
marie_ai.egg-info/requires.txt
marie_ai.egg-info/top_level.txt
